Workbook

Sheet 原材料、燃料、动力购进、库存及价格表
A1: 原材料、燃料、动力购进、库存及价格表
A2: 填报单位： | B2: 油田气生产计划部 | D2: 日期： | E2: 2025-05 | G2: =取值!A1&取值!B1&取值!C1 -> 报表生成时间：2025-06-01 8:00:00
A3: 指标名称 | B3: 期初库存 （吨） | C3: 购进量 (吨) | E3: 消费量 (吨) | G3: 期末库存 （吨） | H3: 价格 (元/吨)(元/Nm3) | I3: 当月金额 （千元） | J3: 累计金额 (千元)
A4: 一、原材料 | C4: 本月 | D4: 累计 | E4: 本月 | F4: 累计
A5: 天然气(Nm3) | C5: 19990403 | D5: =_xlfn.IFERROR(SUM(C5,取值!D5),"") -> 93082172 | E5: =C5 -> 19990403 | F5: =D5 -> 93082172 | H5: 0.69 | I5: 13793.378 | J5: =_xlfn.IFERROR(SUM(I5,取值!I5),"") -> 51070.18
A6: 甲醇 | B6: 3351.29 | C6: 7060.22 | D6: =_xlfn.IFERROR(SUM(C6,取值!D6),"") -> 33355.84 | E6: 7189 | F6: =_xlfn.IFERROR(SUM(E6,取值!F6),"") -> 32987 | G6: =_xlfn.IFERROR(SUM(B6,C6)-SUM(E6),"") -> 3222.51
A7: 醋酐 | B7: 144.38 | C7: 0 | D7: =_xlfn.IFERROR(SUM(C7,取值!D7),"") -> 248.66 | E7: 0 | F7: =_xlfn.IFERROR(SUM(E7,取值!F7),"") -> 186.2 | G7: =_xlfn.IFERROR(SUM(B7,C7)-SUM(E7),"") -> 144.38
A8: 二、燃料
A9: 原 煤 | B9: 3703.38 | C9: 32962.86 | D9: =_xlfn.IFERROR(SUM(C9,取值!D10),"") -> 151680.52 | E9: 30123.35 | F9: =_xlfn.IFERROR(SUM(E9,取值!F10),"") -> 149274.79 | G9: =_xlfn.IFERROR(SUM(B9,C9)-SUM(E9),"") -> 6542.89 | H9: 628.73 | I9: 20724.739 | J9: =_xlfn.IFERROR(SUM(I9,取值!I10),"") -> 106670.23
A10: 原煤热值 | B10: 当月热值 （cal/g） | C10: 6106.83 | D10: 年累计热值 （cal/g） | E10: 6008.09
A11: 天然气(Nm3) | C11: 1752597 | D11: =_xlfn.IFERROR(SUM(C11,取值!D9),"") -> 7356735 | E11: =C11 -> 1752597 | F11: =D11 -> 7356735 | H11: 0.69 | I11: 1209.2919 | J11: =_xlfn.IFERROR(SUM(I11,取值!I9),"") -> 4067.3993
A12: 三、成品 | B12: 期初库存（吨） | C12: 交库量 | D12: 销售量 | E12: 期末库存（吨)
A13: BDO | B13: 326.39 | C13: 8004.69 | D13: 4794.78 | E13: 3536.3
A14: PTMEG1800 | B14: 7138.61 | C14: 0 | D14: 90.18 | E14: 7048.43
A15: PTMEG2000 | B15: 0 | C15: 0 | D15: 0 | E15: 0
A16: 聚酯级乙二醇 | B16: 1472.5 | C16: 4642 | D16: 2329.92 | E16: 3784.58
A17: 轻质多元醇 | B17: 42.61 | C17: 1663.24 | D17: 1387.84 | E17: 318.01
A18: 混合醇 | B18: 37.84 | C18: 197.8 | D18: 196.14 | E18: 39.5
A19: 四、动力 | B19: 购进量 | D19: 工业消费 | F19: 非工业消费 | H19: 价格(元/度) | I19: 当月金额 | J19: 累计金额 （千元）
B20: 本月 | C20: 累计 | D20: 本月 | E20: 累计 | F20: 本月 | G20: 累计
A21: 购电（万千瓦时） | B21: 3051.83 | C21: =_xlfn.IFERROR(SUM(B21,取值!D19),"") -> 14548.68 | D21: 3033.54 | E21: =_xlfn.IFERROR(SUM(D21,取值!F19),"") -> 14415.62 | F21: 18.29 | G21: =_xlfn.IFERROR(SUM(F21,取值!H19),"") -> 133.06 | H21: 0.64 | I21: 19531.712 | J21: =_xlfn.IFERROR(SUM(I21,取值!I19),"") -> 86517.185
A22: 发电量（万度） | B22: / | C22: / | D22: 564.73 | E22: =_xlfn.IFERROR(SUM(D22,取值!F20),"") -> 2615.88 | F22: / | G22: / | H22: 0.29 | I22: 1637.72 | J22: =_xlfn.IFERROR(SUM(I22,取值!I20),"") -> 7585.779
A23: 能源购进金额：指各种能源按照购进价格计算的能源购进量，以价值量（金额）表示，含增值税。计算能源购进金额时要注意： 1、价值量指标要与实物量指标相一致。即计算实物量的，亦计算价值量，反之亦然； 2、已验收入库尚未结算，购货发票未到，购进量以实际验收数量计算，购进金额以货物的上期平均价或合同价格乘购进量计算，待结算后再作调整； 3、能源购进金额不包括运输、装卸费用。
A26: 单位领导: | B26: 王亮 | E26: 审核人： | F26: 李刚 | I26: 填报人: | J26: 南文文

Sheet 取值
A1: 报表生成时间： | B1: 2025-06-01 | C1: 8:00:00
A3: 指标名称 | B3: 期初库存（吨） | C3: 购进量(吨) | E3: 消费量(吨) | G3: 期末库存（吨） | H3: 金额(千元) | I3: 累计金额(千元)
A4: 一、原材料 | C4: 本月 | D4: 累计 | E4: 本月 | F4: 累计
A5: 天然气(m3) | C5: 19990403 | D5: 73091769 | I5: 37276.802
A6: 甲醇 | B6: 3351.29 | C6: 7060.22 | D6: 26295.62 | E6: =_xlfn.IFERROR(SUM(E25,E26,E27,E28),"") -> 7189 | F6: 25798
A7: 醋酐 | B7: 144.38 | C7: 0 | D7: 248.66 | E7: 0 | F7: 186.2
A8: 二、燃料
A9: 天然气（燃料）(m3) | C9: 1752597 | D9: 5604138 | I9: 2858.1074
A10: 煤 | B10: 3703.38 | C10: 32962.86 | D10: 118717.66 | E10: 30123.35 | F10: 119151.44 | I10: 85945.493
A11: 四、成品 | B11: 期初库存（吨） | C11: 交库量 | D11: 销售量 | E11: 期末库存（吨)
A12: BDO | B12: 326.39 | C12: 8004.69 | D12: 4794.78 | E12: 3536.3
A13: PTMEG1800 | B13: 7138.61 | C13: 0 | D13: 90.18 | E13: 7048.43
A14: PTMEG2000 | B14: 0 | C14: 0 | D14: 0 | E14: 0
A15: 聚酯级乙二醇 | B15: 1472.5 | C15: 4642 | D15: 2329.92 | E15: 3784.58
A16: 轻质多元醇 | B16: 42.61 | C16: 1663.24 | D16: 1387.84 | E16: 318.01
A17: 混合醇 | B17: 37.84 | C17: 197.8 | D17: 196.14 | E17: 39.5
C18: 本月购进/发电 | D18: 累计购进/发电 | E18: 工业消费 | F18: 累计工业消费
A19: 购电（兆瓦时） | D19: 11496.85 | F19: 11382.08 | H19: 114.77 | I19: 66985.473
A20: 发电量（万度） | F20: 2051.15 | I20: 5948.059
E25: 6275.5
E26: 0
E27: 842
E28: 71.5
